[
    {
        "lang": "mishnaic", 
        "confidence": [
            0.026870355014624814, 
            1.5731296449853753
        ], 
        "word": "רבן"
    }, 
    {
        "lang": "mishnaic", 
        "confidence": [
            0.033896509648844705, 
            1.5661034903511553
        ], 
        "word": "שמעון"
    }, 
    {
        "lang": "mishnaic", 
        "confidence": [
            0.049474024831322634, 
            2.0505259751686773
        ], 
        "word": "בן"
    }, 
    {
        "lang": "mishnaic", 
        "confidence": [
            0.04094297568592167, 
            2.0590570243140784
        ], 
        "word": "גמליאל"
    }, 
    {
        "lang": "mishnaic", 
        "confidence": [
            0.040176853095716066, 
            2.059823146904284
        ], 
        "word": "אומר"
    }, 
    {
        "lang": "mishnaic", 
        "confidence": [
            0.5287812816246856, 
            1.5712187183753143
        ], 
        "word": "אף"
    }, 
    {
        "lang": "aramaic", 
        "confidence": [
            1.1017974904477652, 
            0.9982025095522349
        ], 
        "word": "שטרי"
    }, 
    {
        "lang": "mishnaic", 
        "confidence": [
            0.5246362968564847, 
            1.5753637031435153
        ], 
        "word": "מקח"
    }, 
    {
        "lang": "mishnaic", 
        "confidence": [
            0.1653406988426978, 
            1.9346593011573021
        ], 
        "word": "וממכר"
    }, 
    {
        "lang": "mishnaic", 
        "confidence": [
            0.3070329473431969, 
            1.7929670526568031
        ], 
        "word": "אין"
    }, 
    {
        "lang": "mishnaic", 
        "confidence": [
            0.33919238594988366, 
            1.7608076140501163
        ], 
        "word": "כותבין"
    }, 
    {
        "lang": "mishnaic", 
        "confidence": [
            0.42598477771647575, 
            1.6740152222835243
        ], 
        "word": "וכן"
    }, 
    {
        "lang": "mishnaic", 
        "confidence": [
            0.21091749318926012, 
            1.8890825068107397
        ], 
        "word": "היה"
    }, 
    {
        "lang": "mishnaic", 
        "confidence": [
            0.035073009422259466, 
            2.0649269905777405
        ], 
        "word": "רבן"
    }, 
    {
        "lang": "mishnaic", 
        "confidence": [
            0.04217175939703911, 
            2.057828240602961
        ], 
        "word": "שמעון"
    }, 
    {
        "lang": "mishnaic", 
        "confidence": [
            0.049474024831322634, 
            2.0505259751686773
        ], 
        "word": "בן"
    }, 
    {
        "lang": "mishnaic", 
        "confidence": [
            0.04094297568592167, 
            2.0590570243140784
        ], 
        "word": "גמליאל"
    }, 
    {
        "lang": "mishnaic", 
        "confidence": [
            0.03658537434313707, 
            2.063414625656863
        ], 
        "word": "אומר"
    }, 
    {
        "lang": "mishnaic", 
        "confidence": [
            0.04347916019525977, 
            2.0565208398047403
        ], 
        "word": "הנותן"
    }, 
    {
        "lang": "mishnaic", 
        "confidence": [
            0.06980531482326728, 
            2.030194685176733
        ], 
        "word": "מתנה"
    }, 
    {
        "lang": "mishnaic", 
        "confidence": [
            0.0918280857029266, 
            2.0081719142970735
        ], 
        "word": "לחברו"
    }, 
    {
        "lang": "mishnaic", 
        "confidence": [
            0.05880678446409253, 
            2.0411932155359076
        ], 
        "word": "והחזיר"
    }, 
    {
        "lang": "mishnaic", 
        "confidence": [
            0.045669945591309685, 
            2.05433005440869
        ], 
        "word": "לו"
    }, 
    {
        "lang": "mishnaic", 
        "confidence": [
            0.058695174984569734, 
            2.0413048250154304
        ], 
        "word": "את"
    }, 
    {
        "lang": "mishnaic", 
        "confidence": [
            0.37346256907848424, 
            1.7265374309215158
        ], 
        "word": "השטר"
    }, 
    {
        "lang": "mishnaic", 
        "confidence": [
            0.7583283395922523, 
            1.3416716604077479
        ], 
        "word": "חזרה"
    }, 
    {
        "lang": "mishnaic", 
        "confidence": [
            0.36694443212853545, 
            1.7330555678714648
        ], 
        "word": "מתנתו"
    }, 
    {
        "lang": "mishnaic", 
        "confidence": [
            0.03620760332281445, 
            2.0637923966771856
        ], 
        "word": "וחכמים"
    }, 
    {
        "lang": "mishnaic", 
        "confidence": [
            0.03620952399170736, 
            2.063790476008293
        ], 
        "word": "אומרים"
    }, 
    {
        "lang": "mishnaic", 
        "confidence": [
            0.1480788232660405, 
            1.9519211767339597
        ], 
        "word": "מתנתו"
    }, 
    {
        "lang": "mishnaic", 
        "confidence": [
            0.4690935246546119, 
            1.6309064753453884
        ], 
        "word": "קיימת"
    }, 
    {
        "lang": "aramaic", 
        "confidence": [
            1.054464809342087, 
            1.0455351906579133
        ], 
        "word": "אמר"
    }, 
    {
        "lang": "aramaic", 
        "confidence": [
            1.30000072284461, 
            0.79999927715539
        ], 
        "word": "מר"
    }, 
    {
        "lang": "mishnaic", 
        "confidence": [
            0.5223015064498101, 
            1.5776984935501899
        ], 
        "word": "חוץ"
    }, 
    {
        "lang": "mishnaic", 
        "confidence": [
            0.03691900586544187, 
            2.063080994134558
        ], 
        "word": "מאחריות"
    }, 
    {
        "lang": "mishnaic", 
        "confidence": [
            0.528902301959751, 
            1.5710976980402491
        ], 
        "word": "שבו"
    }, 
    {
        "lang": "aramaic", 
        "confidence": [
            1.601321048930255, 
            0.49867895106974514
        ], 
        "word": "מאי"
    }, 
    {
        "lang": "aramaic", 
        "confidence": [
            1.9915216116460943, 
            0.10847838835390584
        ], 
        "word": "טעמא"
    }, 
    {
        "lang": "aramaic", 
        "confidence": [
            1.8758635494489733, 
            0.2241364505510269
        ], 
        "word": "א\"ר"
    }, 
    {
        "lang": "aramaic", 
        "confidence": [
            1.5026536357848639, 
            0.5973463642151363
        ], 
        "word": "ספרא"
    }, 
    {
        "lang": "mishnaic", 
        "confidence": [
            0.5241337748641486, 
            1.5758662251358513
        ], 
        "word": "לפי"
    }, 
    {
        "lang": "mishnaic", 
        "confidence": [
            0.03839792373200866, 
            2.0616020762679916
        ], 
        "word": "שאין"
    }, 
    {
        "lang": "mishnaic", 
        "confidence": [
            0.2517676595814397, 
            1.8482323404185603
        ], 
        "word": "כותבין"
    }, 
    {
        "lang": "mishnaic", 
        "confidence": [
            0.4994174032686489, 
            1.6005825967313512
        ], 
        "word": "שני"
    }, 
    {
        "lang": "mishnaic", 
        "confidence": [
            0.25800412424594354, 
            1.8419958757540564
        ], 
        "word": "שטרות"
    }, 
    {
        "lang": "mishnaic", 
        "confidence": [
            0.0640627092019441, 
            2.035937290798056
        ], 
        "word": "על"
    }, 
    {
        "lang": "mishnaic", 
        "confidence": [
            0.04939656341520049, 
            2.0506034365847996
        ], 
        "word": "שדה"
    }, 
    {
        "lang": "mishnaic", 
        "confidence": [
            0.5270790159723019, 
            1.5729209840276983
        ], 
        "word": "אחת"
    }, 
    {
        "lang": "aramaic", 
        "confidence": [
            1.6004783317128248, 
            0.4995216682871753
        ], 
        "word": "דלמא"
    }, 
    {
        "lang": "aramaic", 
        "confidence": [
            1.6013606349498097, 
            0.49863936505019046
        ], 
        "word": "אזיל"
    }, 
    {
        "lang": "mishnaic", 
        "confidence": [
            0.5295293231954791, 
            1.5704706768045211
        ], 
        "word": "בעל"
    }, 
    {
        "lang": "mishnaic", 
        "confidence": [
            0.5260937448129664, 
            1.5739062551870338
        ], 
        "word": "חוב"
    }, 
    {
        "lang": "aramaic", 
        "confidence": [
            1.5983306356644276, 
            0.5016693643355726
        ], 
        "word": "טריף"
    }, 
    {
        "lang": "aramaic", 
        "confidence": [
            2.0867866485915703, 
            0.013213351408429705
        ], 
        "word": "ליה"
    }, 
    {
        "lang": "aramaic", 
        "confidence": [
            2.0870589585779955, 
            0.012941041422004624
        ], 
        "word": "להאי"
    }, 
    {
        "lang": "aramaic", 
        "confidence": [
            2.087332186306056, 
            0.012667813693944166
        ], 
        "word": "ואזיל"
    }, 
    {
        "lang": "aramaic", 
        "confidence": [
            2.0572728044374466, 
            0.042727195562553125
        ], 
        "word": "האי"
    }, 
    {
        "lang": "aramaic", 
        "confidence": [
            2.021119712126254, 
            0.07888028787374607
        ], 
        "word": "ומפיק"
    }, 
    {
        "lang": "aramaic", 
        "confidence": [
            2.057112934699278, 
            0.04288706530072209
        ], 
        "word": "חד"
    }, 
    {
        "lang": "aramaic", 
        "confidence": [
            1.5984944805034353, 
            0.5015055194965646
        ], 
        "word": "וטריף"
    }, 
    {
        "lang": "mishnaic", 
        "confidence": [
            0.5353951749838459, 
            1.5646048250161542
        ], 
        "word": "לקוחות"
    }, 
    {
        "lang": "mishnaic", 
        "confidence": [
            0.5497523782257467, 
            1.5502476217742533
        ], 
        "word": "ואמר"
    }, 
    {
        "lang": "aramaic", 
        "confidence": [
            1.1227291116477534, 
            0.9772708883522466
        ], 
        "word": "ליה"
    }, 
    {
        "lang": "mishnaic", 
        "confidence": [
            0.525907572561144, 
            1.5740924274388561
        ], 
        "word": "לבעל"
    }, 
    {
        "lang": "mishnaic", 
        "confidence": [
            0.03890369289323541, 
            2.061096307106765
        ], 
        "word": "חוב"
    }, 
    {
        "lang": "mishnaic", 
        "confidence": [
            0.12146864035208534, 
            1.9785313596479146
        ], 
        "word": "שוף"
    }, 
    {
        "lang": "mishnaic", 
        "confidence": [
            0.7010496990686269, 
            1.3989503009313733
        ], 
        "word": "לי"
    }, 
    {
        "lang": "aramaic", 
        "confidence": [
            1.3330729832248842, 
            0.7669270167751159
        ], 
        "word": "דאיקום"
    }, 
    {
        "lang": "aramaic", 
        "confidence": [
            1.3324870873024368, 
            0.7675129126975632
        ], 
        "word": "בה"
    }, 
    {
        "lang": "aramaic", 
        "confidence": [
            1.743282995486541, 
            0.3567170045134592
        ], 
        "word": "והדר"
    }, 
    {
        "lang": "aramaic", 
        "confidence": [
            1.6343511350546662, 
            0.4656488649453339
        ], 
        "word": "תא"
    }, 
    {
        "lang": "aramaic", 
        "confidence": [
            1.0664384042211186, 
            1.0335615957788815
        ], 
        "word": "טירפן"
    }, 
    {
        "lang": "aramaic", 
        "confidence": [
            1.5713521860311077, 
            0.5286478139688924
        ], 
        "word": "ומפיק"
    }, 
    {
        "lang": "aramaic", 
        "confidence": [
            2.0569237011091976, 
            0.04307629889080229
        ], 
        "word": "אחרינא"
    }, 
    {
        "lang": "aramaic", 
        "confidence": [
            2.086935363143218, 
            0.0130646368567821
        ], 
        "word": "והדר"
    }, 
    {
        "lang": "aramaic", 
        "confidence": [
            2.087015852714991, 
            0.01298414728500891
        ], 
        "word": "אזיל"
    }, 
    {
        "lang": "aramaic", 
        "confidence": [
            1.5985077956625504, 
            0.5014922043374497
        ], 
        "word": "טריף"
    }, 
    {
        "lang": "mishnaic", 
        "confidence": [
            0.9722394226930857, 
            1.1277605773069144
        ], 
        "word": "לקוחות"
    }, 
    {
        "lang": "aramaic", 
        "confidence": [
            1.5019365035824639, 
            0.598063496417536
        ], 
        "word": "אחריני"
    }, 
    {
        "lang": "aramaic", 
        "confidence": [
            2.027550368166013, 
            0.07244963183398717
        ], 
        "word": "וכיון"
    }, 
    {
        "lang": "aramaic", 
        "confidence": [
            2.0773922874670623, 
            0.02260771253293795
        ], 
        "word": "דקרעניה"
    }, 
    {
        "lang": "aramaic", 
        "confidence": [
            2.0852740959637144, 
            0.014725904036285507
        ], 
        "word": "לשטרא"
    }, 
    {
        "lang": "aramaic", 
        "confidence": [
            2.0858741839670802, 
            0.01412581603292008
        ], 
        "word": "דמלוה"
    }, 
    {
        "lang": "aramaic", 
        "confidence": [
            2.087006422802408, 
            0.01299357719759214
        ], 
        "word": "במאי"
    }, 
    {
        "lang": "aramaic", 
        "confidence": [
            2.0873528257548775, 
            0.012647174245122508
        ], 
        "word": "הדר"
    }, 
    {
        "lang": "aramaic", 
        "confidence": [
            1.6334722614021668, 
            0.4665277385978333
        ], 
        "word": "טריף"
    }, 
    {
        "lang": "mishnaic", 
        "confidence": [
            0.7192759806535436, 
            1.3807240193464565
        ], 
        "word": "לה"
    }, 
    {
        "lang": "mishnaic", 
        "confidence": [
            0.8197450779257698, 
            1.2802549220742303
        ], 
        "word": "וכי"
    }, 
    {
        "lang": "aramaic", 
        "confidence": [
            1.7160517416167171, 
            0.3839482583832829
        ], 
        "word": "תימא"
    }, 
    {
        "lang": "aramaic", 
        "confidence": [
            2.0456858658788013, 
            0.054314134121198746
        ], 
        "word": "דלא"
    }, 
    {
        "lang": "aramaic", 
        "confidence": [
            1.996847478452085, 
            0.10315252154791485
        ], 
        "word": "קרעניה"
    }, 
    {
        "lang": "aramaic", 
        "confidence": [
            1.7494161588535593, 
            0.35058384114644087
        ], 
        "word": "והא"
    }, 
    {
        "lang": "aramaic", 
        "confidence": [
            1.4362218769643196, 
            0.6637781230356806
        ], 
        "word": "אמר"
    }, 
    {
        "lang": "aramaic", 
        "confidence": [
            1.3222729220861578, 
            0.7777270779138424
        ], 
        "word": "רב"
    }, 
    {
        "lang": "mishnaic", 
        "confidence": [
            0.6859946884693072, 
            1.414005311530693
        ], 
        "word": "נחמן"
    }, 
    {
        "lang": "mishnaic", 
        "confidence": [
            0.8121501601035666, 
            1.2878498398964335
        ], 
        "word": "כל"
    }, 
    {
        "lang": "aramaic", 
        "confidence": [
            1.72227322363598, 
            0.3777267763640201
        ], 
        "word": "טירפא"
    }, 
    {
        "lang": "aramaic", 
        "confidence": [
            2.085593776274803, 
            0.014406223725197252
        ], 
        "word": "דלא"
    }, 
    {
        "lang": "aramaic", 
        "confidence": [
            2.082599088715262, 
            0.01740091128473773
        ], 
        "word": "כתיב"
    }, 
    {
        "lang": "aramaic", 
        "confidence": [
            2.043848327270136, 
            0.05615167272986413
        ], 
        "word": "ביה"
    }, 
    {
        "lang": "aramaic", 
        "confidence": [
            1.9958820229965806, 
            0.10411797700341938
        ], 
        "word": "קרעניה"
    }, 
    {
        "lang": "aramaic", 
        "confidence": [
            2.0441022567633373, 
            0.05589774323666287
        ], 
        "word": "לשטרא"
    }, 
    {
        "lang": "aramaic", 
        "confidence": [
            1.7694666281978733, 
            0.3305333718021267
        ], 
        "word": "דמלוה"
    }, 
    {
        "lang": "aramaic", 
        "confidence": [
            1.3909078538093516, 
            0.7090921461906485
        ], 
        "word": "לאו"
    }, 
    {
        "lang": "aramaic", 
        "confidence": [
            1.355327176228562, 
            0.7446728237714382
        ], 
        "word": "טירפא"
    }, 
    {
        "lang": "mishnaic", 
        "confidence": [
            0.826830649725759, 
            1.2731693502742412
        ], 
        "word": "הוא"
    }, 
    {
        "lang": "mishnaic", 
        "confidence": [
            0.9098744006248649, 
            1.1901255993751354
        ], 
        "word": "וכל"
    }, 
    {
        "lang": "aramaic", 
        "confidence": [
            1.7410228578350204, 
            0.35897714216497956
        ], 
        "word": "אדרכתא"
    }, 
    {
        "lang": "aramaic", 
        "confidence": [
            2.085476301339596, 
            0.014523698660403837
        ], 
        "word": "דלא"
    }, 
    {
        "lang": "aramaic", 
        "confidence": [
            1.7401300299133886, 
            0.35986997008661137
        ], 
        "word": "כתיב"
    }, 
    {
        "lang": "aramaic", 
        "confidence": [
            1.290416397906014, 
            0.8095836020939862
        ], 
        "word": "בה"
    }, 
    {
        "lang": "aramaic", 
        "confidence": [
            1.6540225004295857, 
            0.44597749957041427
        ], 
        "word": "קרעניה"
    }, 
    {
        "lang": "aramaic", 
        "confidence": [
            1.7293473923838456, 
            0.37065260761615454
        ], 
        "word": "לטירפא"
    }, 
    {
        "lang": "aramaic", 
        "confidence": [
            1.3909360914351616, 
            0.7090639085648385
        ], 
        "word": "לאו"
    }, 
    {
        "lang": "aramaic", 
        "confidence": [
            1.3550687313711074, 
            0.7449312686288926
        ], 
        "word": "אדרכתא"
    }, 
    {
        "lang": "mishnaic", 
        "confidence": [
            0.8267131747905524, 
            1.2732868252094476
        ], 
        "word": "הוא"
    }, 
    {
        "lang": "mishnaic", 
        "confidence": [
            0.9100098692545205, 
            1.1899901307454797
        ], 
        "word": "וכל"
    }, 
    {
        "lang": "aramaic", 
        "confidence": [
            1.741320888820263, 
            0.35867911117973716
        ], 
        "word": "שומא"
    }, 
    {
        "lang": "aramaic", 
        "confidence": [
            2.085611769969252, 
            0.014388230030748198
        ], 
        "word": "דלא"
    }, 
    {
        "lang": "aramaic", 
        "confidence": [
            2.082599088715262, 
            0.01740091128473773
        ], 
        "word": "כתיב"
    }, 
    {
        "lang": "aramaic", 
        "confidence": [
            2.043848327270136, 
            0.05615167272986413
        ], 
        "word": "ביה"
    }, 
    {
        "lang": "aramaic", 
        "confidence": [
            1.9966207525650193, 
            0.10337924743498074
        ], 
        "word": "קרעניה"
    }, 
    {
        "lang": "aramaic", 
        "confidence": [
            1.7296316177176774, 
            0.3703683822823227
        ], 
        "word": "לאדרכתא"
    }, 
    {
        "lang": "aramaic", 
        "confidence": [
            1.391200753398377, 
            0.7087992466016229
        ], 
        "word": "לאו"
    }, 
    {
        "lang": "aramaic", 
        "confidence": [
            1.3832975181479252, 
            0.7167024818520749
        ], 
        "word": "שומא"
    }, 
    {
        "lang": "mishnaic", 
        "confidence": [
            0.8967823899836191, 
            1.2032176100163807
        ], 
        "word": "היא"
    }, 
    {
        "lang": "mishnaic", 
        "confidence": [
            0.9567758536818495, 
            1.1432241463181505
        ], 
        "word": "לא"
    }, 
    {
        "lang": "aramaic", 
        "confidence": [
            1.749761670766362, 
            0.35023832923363823
        ], 
        "word": "צריכא"
    }, 
    {
        "lang": "aramaic", 
        "confidence": [
            1.816762779159564, 
            0.283237220840436
        ], 
        "word": "דקאתי"
    }, 
    {
        "lang": "aramaic", 
        "confidence": [
            1.445515055393083, 
            0.6544849446069172
        ], 
        "word": "מכח"
    }, 
    {
        "lang": "aramaic", 
        "confidence": [
            1.4173606802102847, 
            0.6826393197897151
        ], 
        "word": "אבהתיה"
    }, 
    {
        "lang": "aramaic", 
        "confidence": [
            1.3877711948988485, 
            0.7122288051011517
        ], 
        "word": "אמר"
    }, 
    {
        "lang": "aramaic", 
        "confidence": [
            1.7915648679421268, 
            0.3084351320578733
        ], 
        "word": "ליה"
    }, 
    {
        "lang": "aramaic", 
        "confidence": [
            1.7411540221572548, 
            0.35884597784274536
        ], 
        "word": "רב"
    }, 
    {
        "lang": "mishnaic", 
        "confidence": [
            0.8431247654313692, 
            1.256875234568631
        ], 
        "word": "אחא"
    }, 
    {
        "lang": "mishnaic", 
        "confidence": [
            0.6871348871793808, 
            1.4128651128206193
        ], 
        "word": "מדפתי"
    }, 
    {
        "lang": "aramaic", 
        "confidence": [
            1.3664302410260545, 
            0.7335697589739456
        ], 
        "word": "לרבינא"
    }, 
    {
        "lang": "aramaic", 
        "confidence": [
            1.552275569372282, 
            0.5477244306277183
        ], 
        "word": "ולמה"
    }, 
    {
        "lang": "aramaic", 
        "confidence": [
            1.8435092630492012, 
            0.2564907369507988
        ], 
        "word": "ליה"
    }, 
    {
        "lang": "aramaic", 
        "confidence": [
            2.08648102020959, 
            0.013518979790410106
        ], 
        "word": "למימר"
    }, 
    {
        "lang": "aramaic", 
        "confidence": [
            1.5991833350947755, 
            0.5008166649052247
        ], 
        "word": "ליה"
    }, 
    {
        "lang": "mishnaic", 
        "confidence": [
            0.525907572561144, 
            1.5740924274388561
        ], 
        "word": "לבעל"
    }, 
    {
        "lang": "mishnaic", 
        "confidence": [
            0.03890369289323541, 
            2.061096307106765
        ], 
        "word": "חוב"
    }, 
    {
        "lang": "mishnaic", 
        "confidence": [
            0.12146864035208534, 
            1.9785313596479146
        ], 
        "word": "שוף"
    }, 
    {
        "lang": "mishnaic", 
        "confidence": [
            0.7024024318722512, 
            1.397597568127749
        ], 
        "word": "לי"
    }, 
    {
        "lang": "aramaic", 
        "confidence": [
            1.6785344506821347, 
            0.42146554931786534
        ], 
        "word": "בהאי"
    }, 
    {
        "lang": "aramaic", 
        "confidence": [
            2.0845457436527544, 
            0.015454256347245524
        ], 
        "word": "ארעא"
    }, 
    {
        "lang": "aramaic", 
        "confidence": [
            1.738679471578719, 
            0.36132052842128104
        ], 
        "word": "ואיקום"
    }, 
    {
        "lang": "aramaic", 
        "confidence": [
            1.3286166488669502, 
            0.7713833511330499
        ], 
        "word": "בה"
    }, 
    {
        "lang": "aramaic", 
        "confidence": [
            1.739171864715221, 
            0.3608281352847789
        ], 
        "word": "תיפוק"
    }, 
    {
        "lang": "aramaic", 
        "confidence": [
            2.0842654615490366, 
            0.01573453845096338
        ], 
        "word": "ליה"
    }, 
    {
        "lang": "aramaic", 
        "confidence": [
            2.086872047843389, 
            0.01312795215661119
        ], 
        "word": "דכיון"
    }, 
    {
        "lang": "aramaic", 
        "confidence": [
            2.0862671624480447, 
            0.01373283755195557
        ], 
        "word": "דנקיט"
    }, 
    {
        "lang": "aramaic", 
        "confidence": [
            2.0782744682056924, 
            0.021725531794307737
        ], 
        "word": "תרי"
    }, 
    {
        "lang": "aramaic", 
        "confidence": [
            2.0704228044199926, 
            0.029577195580007227
        ], 
        "word": "שטרי"
    }, 
    {
        "lang": "aramaic", 
        "confidence": [
            2.0799954259059983, 
            0.020004574094001852
        ], 
        "word": "טריף"
    }, 
    {
        "lang": "aramaic", 
        "confidence": [
            2.0873280920990096, 
            0.012671907900990407
        ], 
        "word": "והדר"
    }, 
    {
        "lang": "aramaic", 
        "confidence": [
            1.6091738734296324, 
            0.4908261265703679
        ], 
        "word": "טריף"
    }, 
    {
        "lang": "mishnaic", 
        "confidence": [
            0.5493244015450146, 
            1.5506755984549854
        ], 
        "word": "אם"
    }, 
    {
        "lang": "mishnaic", 
        "confidence": [
            0.5398149278405687, 
            1.5601850721594315
        ], 
        "word": "כן"
    }, 
    {
        "lang": "aramaic", 
        "confidence": [
            1.2336981951095223, 
            0.8663018048904779
        ], 
        "word": "נפישי"
    }, 
    {
        "lang": "mishnaic", 
        "confidence": [
            0.8254634562998805, 
            1.2745365437001197
        ], 
        "word": "עליה"
    }, 
    {
        "lang": "mishnaic", 
        "confidence": [
            0.3140438581452823, 
            1.7859561418547178
        ], 
        "word": "בעלי"
    }, 
    {
        "lang": "mishnaic", 
        "confidence": [
            0.30012010380095216, 
            1.799879896199048
        ], 
        "word": "דינין"
    }, 
    {
        "lang": "mishnaic", 
        "confidence": [
            0.7200308259780825, 
            1.3799691740219178
        ], 
        "word": "ולכתוב"
    }, 
    {
        "lang": "aramaic", 
        "confidence": [
            1.6508268000082695, 
            0.44917319999173067
        ], 
        "word": "להאי"
    }, 
    {
        "lang": "aramaic", 
        "confidence": [
            2.0051356997740903, 
            0.09486430022590991
        ], 
        "word": "שטרא"
    }, 
    {
        "lang": "aramaic", 
        "confidence": [
            1.4720967674806653, 
            0.627903232519335
        ], 
        "word": "מעליא"
    }, 
    {
        "lang": "mishnaic", 
        "confidence": [
            1.0465358729277474, 
            1.053464127072253
        ], 
        "word": "ולכתוב"
    }, 
    {
        "lang": "aramaic", 
        "confidence": [
            1.1637827828816032, 
            0.936217217118397
        ], 
        "word": "תברא"
    }, 
    {
        "lang": "mishnaic", 
        "confidence": [
            0.6503791668940886, 
            1.4496208331059117
        ], 
        "word": "למוכר"
    }, 
    {
        "lang": "mishnaic", 
        "confidence": [
            0.7893018234691014, 
            1.3106981765308987
        ], 
        "word": "כל"
    }, 
    {
        "lang": "aramaic", 
        "confidence": [
            1.6680304344246608, 
            0.43196956557533933
        ], 
        "word": "שטרי"
    }, 
    {
        "lang": "aramaic", 
        "confidence": [
            1.521500790508461, 
            0.5784992094915393
        ], 
        "word": "דיפקון"
    }, 
    {
        "lang": "mishnaic", 
        "confidence": [
            1.0037363634571723, 
            1.0962636365428278
        ], 
        "word": "על"
    }, 
    {
        "lang": "aramaic", 
        "confidence": [
            1.6120923217123861, 
            0.487907678287614
        ], 
        "word": "ארעא"
    }, 
    {
        "lang": "aramaic", 
        "confidence": [
            1.598773783192305, 
            0.501226216807695
        ], 
        "word": "דא"
    }, 
    {
        "lang": "mishnaic", 
        "confidence": [
            1.011974140281124, 
            1.088025859718876
        ], 
        "word": "פסולין"
    }, 
    {
        "lang": "aramaic", 
        "confidence": [
            1.133737941662832, 
            0.9662620583371682
        ], 
        "word": "לבר"
    }, 
    {
        "lang": "aramaic", 
        "confidence": [
            1.0647893790197356, 
            1.0352106209802645
        ], 
        "word": "מן"
    }, 
    {
        "lang": "aramaic", 
        "confidence": [
            1.6222562089010464, 
            0.47774379109895354
        ], 
        "word": "דיפוק"
    }, 
    {
        "lang": "aramaic", 
        "confidence": [
            2.0872891139736742, 
            0.01271088602632586
        ], 
        "word": "בזמנא"
    }, 
    {
        "lang": "aramaic", 
        "confidence": [
            2.0846201717545805, 
            0.015379828245419308
        ], 
        "word": "דא"
    }, 
    {
        "lang": "aramaic", 
        "confidence": [
            2.080884032390463, 
            0.01911596760953717
        ], 
        "word": "אמרוה"
    }, 
    {
        "lang": "aramaic", 
        "confidence": [
            2.084215200747135, 
            0.015784799252865415
        ], 
        "word": "רבנן"
    }, 
    {
        "lang": "aramaic", 
        "confidence": [
            2.0870262856879602, 
            0.01297371431203969
        ], 
        "word": "קמיה"
    }, 
    {
        "lang": "aramaic", 
        "confidence": [
            2.0867197060329614, 
            0.01328029396703868
        ], 
        "word": "דרב"
    }, 
    {
        "lang": "aramaic", 
        "confidence": [
            2.0810909879418986, 
            0.018909012058101263
        ], 
        "word": "פפא"
    }, 
    {
        "lang": "aramaic", 
        "confidence": [
            1.6213450902440834, 
            0.47865490975591657
        ], 
        "word": "ואמרי"
    }, 
    {
        "lang": "aramaic", 
        "confidence": [
            1.0832090116007562, 
            1.0167909883992439
        ], 
        "word": "לה"
    }, 
    {
        "lang": "aramaic", 
        "confidence": [
            1.6330594433637466, 
            0.46694055663625356
        ], 
        "word": "קמיה"
    }, 
    {
        "lang": "aramaic", 
        "confidence": [
            1.5989421668862138, 
            0.5010578331137865
        ], 
        "word": "דרב"
    }, 
    {
        "lang": "mishnaic", 
        "confidence": [
            0.5259124298960758, 
            1.5740875701039245
        ], 
        "word": "אשי"
    }, 
    {
        "lang": "mishnaic", 
        "confidence": [
            0.03868936795311437, 
            2.0613106320468857
        ], 
        "word": "זאת"
    }, 
    {
        "lang": "mishnaic", 
        "confidence": [
            0.15768405778676067, 
            1.9423159422132394
        ], 
        "word": "אומרת"
    }, 
    {
        "lang": "mishnaic", 
        "confidence": [
            0.3039862212902162, 
            1.7960137787097838
        ], 
        "word": "אין"
    }, 
    {
        "lang": "mishnaic", 
        "confidence": [
            0.16609640536553608, 
            1.933903594634464
        ], 
        "word": "כותבין"
    }, 
    {
        "lang": "mishnaic", 
        "confidence": [
            0.036970966023276416, 
            1.5630290339767237
        ], 
        "word": "שובר"
    }
]